topoembedx/__init__.py
topoembedx/_version.py
topoembedx/exception.py
topoembedx/neighborhood.py
topoembedx/classes/__init__.py
topoembedx/classes/cell2vec.py
topoembedx/classes/cell_diff2vec.py
topoembedx/classes/deepcell.py
topoembedx/classes/higher_order_laplacian_eigenmaps.py
topoembedx/classes/hoglee.py
topoembedx/classes/hope.py
topoembedx/classes/random_walks.py
topoembedx-0.1.0.dist-info/licenses/LICENSE
topoembedx-0.1.0.dist-info/METADATA
topoembedx-0.1.0.dist-info/WHEEL
topoembedx-0.1.0.dist-info/top_level.txt
topoembedx-0.1.0.dist-info/RECORD
