Metadata-Version: 2.4
Name: TopoEmbedX
Version: 0.1.0
Summary: Representation Learning on Topological Domains
Author-email: Mustafa Hajij <mhajij@usfca.edu>, Mathilde Papillon <papillon@ucsb.edu>, Florian Frantzen <frantzen@netsci.rwth-aachen.de>
License-Expression: MIT
Project-URL: documentation, https://pyt-team.github.io/topoembedx/
Project-URL: source, https://github.com/pyt-team/TopoEmbedX/
Classifier: Development Status :: 3 - Alpha
Classifier: Intended Audience :: Developers
Classifier: Intended Audience :: Science/Research
Classifier: Operating System :: OS Independent
Classifier: Programming Language :: Python :: 3
Classifier: Programming Language :: Python :: 3 :: Only
Classifier: Programming Language :: Python :: 3.12
Classifier: Topic :: Scientific/Engineering
Classifier: Topic :: Scientific/Engineering :: Mathematics
Classifier: Topic :: Scientific/Engineering :: Artificial Intelligence
Requires-Python: >=3.12
License-File: LICENSE
Requires-Dist: numpy
Requires-Dist: networkx
Requires-Dist: pyrandwalk
Requires-Dist: scipy
Requires-Dist: toponetx
Requires-Dist: karateclub
Requires-Dist: pygsp
Dynamic: license-file
